<annotation><folder>open_images_volume</folder><filename>4596800a7e27be78.jpg</filename><path>/mnt/open_images_volume/4596800a7e27be78.jpg</path><source><database>Unknown</database></source><size><width>1024</width><height>731</height><depth>3</depth></size><segmented>0</segmented><object><name>Bus</name><pose>Unspecified</pose><truncated>0</truncated><difficult>0</difficult><bndbox><xmin>3</xmin><ymin>5</ymin><xmax>255</xmax><ymax>554</ymax></bndbox></object><object><name>Bus</name><pose>Unspecified</pose><truncated>0</truncated><difficult>0</difficult><bndbox><xmin>238</xmin><ymin>170</ymin><xmax>280</xmax><ymax>365</ymax></bndbox></object><object><name>Bus</name><pose>Unspecified</pose><truncated>0</truncated><difficult>0</difficult><bndbox><xmin>246</xmin><ymin>49</ymin><xmax>781</xmax><ymax>664</ymax></bndbox></object><object><name>Bus</name><pose>Unspecified</pose><truncated>0</truncated><difficult>0</difficult><bndbox><xmin>773</xmin><ymin>127</ymin><xmax>1023</xmax><ymax>577</ymax></bndbox></object></annotation>