<annotation><folder>open_images_volume</folder><filename>c70a1a391c1ef6f8.jpg</filename><path>/mnt/open_images_volume/c70a1a391c1ef6f8.jpg</path><source><database>Unknown</database></source><size><width>1024</width><height>819</height><depth>3</depth></size><segmented>0</segmented><object><name>Car</name><pose>Unspecified</pose><truncated>0</truncated><difficult>0</difficult><bndbox><xmin>0</xmin><ymin>0</ymin><xmax>1023</xmax><ymax>818</ymax></bndbox></object><object><name>Car</name><pose>Unspecified</pose><truncated>0</truncated><difficult>0</difficult><bndbox><xmin>314</xmin><ymin>343</ymin><xmax>659</xmax><ymax>534</ymax></bndbox></object><object><name>Car</name><pose>Unspecified</pose><truncated>0</truncated><difficult>0</difficult><bndbox><xmin>720</xmin><ymin>360</ymin><xmax>732</xmax><ymax>371</ymax></bndbox></object></annotation>